MANIFEST.in
setup.py
bricklayer/__init__.py
bricklayer/models.py
bricklayer/tests.py
bricklayer/utils.py
bricklayer/views.py
bricklayer/management/__init__.py
bricklayer/management/commands/__init__.py
bricklayer/management/commands/generate.py
bricklayer/management/commands/generateadmin.py
bricklayer/management/commands/generatecommand.py
bricklayer/management/commands/generatecrud.py
bricklayer/management/commands/generateform.py
bricklayer/management/commands/generatetest.py
bricklayer/management/commands/generatetestpackage.py
bricklayer/management/commands/testcommand.py
bricklayer/templates/addtest.py.template
bricklayer/templates/admin.py.template
bricklayer/templates/appcommand.py.template
bricklayer/templates/command.init.py.template
bricklayer/templates/command.py.template
bricklayer/templates/confirm_delete.html.template
bricklayer/templates/detail.html.template
bricklayer/templates/form.html.template
bricklayer/templates/forms.py.template
bricklayer/templates/list.html.template
bricklayer/templates/test.py.template
bricklayer/templates/tests.py.template
bricklayer/templates/urls.py.template
bricklayer/templates/views.py.template
bricklayer/testsuite/__init__.py
bricklayer/testsuite/bricklayer_tests.py
bricklayer/testsuite/generateadmin.py
bricklayer/testsuite/generatecommand.py
bricklayer/testsuite/generatecrud.py
bricklayer/testsuite/generateform.py
bricklayer/testsuite/generatetest.py
bricklayer/testsuite/generatetestpackage.py
bricklayer/testsuite/testsuite.py
django_bricklayer.egg-info/PKG-INFO
django_bricklayer.egg-info/SOURCES.txt
django_bricklayer.egg-info/dependency_links.txt
django_bricklayer.egg-info/requires.txt
django_bricklayer.egg-info/top_level.txt