Metadata-Version: 1.1
Name: django-bricklayer
Version: 0.3.3
Summary: Django application providing command-lines utilities similar to Ruby on Rails 'scaffold' command.
Home-page: https://github.com/Ianus/bricklayer/
Author: Luca Adalberto Vandro
Author-email: lucavandro@gmail.com
License: UNKNOWN
Download-URL: https://github.com/Ianus/bricklayer/archive/master.zip
Platform: UNKNOWN
Classifier: Framework :: Django
Classifier: Intended Audience :: Developers
Classifier: License :: OSI Approved :: BSD License
Classifier: Operating System :: OS Independent
Classifier: Topic :: Software Development
